vinehoollm/__init__.py
vinehoollm/client.py
vinehoollm/types.py
vinehoollm-0.2.0.dist-info/METADATA
vinehoollm-0.2.0.dist-info/WHEEL
vinehoollm-0.2.0.dist-info/top_level.txt
vinehoollm-0.2.0.dist-info/RECORD
