Metadata-Version: 2.2
Name: vinehoollm
Version: 0.2.0
Summary: A Python package for interacting with OpenAI-compatible LLMs
Home-page: https://github.com/vinehoo/vinehoollm
Author: Vinehoo
Author-email: wei.du@vinehoo.com
Classifier: Development Status :: 3 - Alpha
Classifier: Intended Audience :: Developers
Classifier: License :: OSI Approved :: MIT License
Classifier: Programming Language :: Python :: 3.8
Classifier: Programming Language :: Python :: 3.9
Classifier: Programming Language :: Python :: 3.10
Classifier: Programming Language :: Python :: 3.11
Requires-Python: >=3.8
Requires-Dist: openai>=1.0.0
Requires-Dist: requests>=2.31.0
Requires-Dist: pydantic>=2.0.0
Requires-Dist: socksio>=1.0.0
Dynamic: author
Dynamic: author-email
Dynamic: classifier
Dynamic: description
Dynamic: description-content-type
Dynamic: home-page
Dynamic: requires-dist
Dynamic: requires-python
Dynamic: summary
